<?xml version="1.0" encoding="utf-8"?>
<tv generator-info-name="yufeilai666" generator-info-url="https://github.com/yufeilai666" source-info-name="epg.pw">
  <channel id="香港卫视">
    <display-name lang="zh">香港卫视</display-name>
    <icon src=""/>
  </channel>
  <programme start="20260420001100 +0800" stop="20260420004100 +0800" channel="香港卫视">
    <title lang="zh">映像</title>
  </programme>
  <programme start="20260420004100 +0800" stop="20260420011100 +0800" channel="香港卫视">
    <title lang="zh">独爱东南</title>
  </programme>
  <programme start="20260420011100 +0800" stop="20260420014500 +0800" channel="香港卫视">
    <title lang="zh">文化超声</title>
  </programme>
  <programme start="20260420014500 +0800" stop="20260420020500 +0800" channel="香港卫视">
    <title lang="zh">亚洲青年说</title>
  </programme>
  <programme start="20260420020500 +0800" stop="20260420024000 +0800" channel="香港卫视">
    <title lang="zh">守心人</title>
  </programme>
  <programme start="20260420024000 +0800" stop="20260420030100 +0800" channel="香港卫视">
    <title lang="zh">西望成都</title>
  </programme>
  <programme start="20260420030100 +0800" stop="20260420033500 +0800" channel="香港卫视">
    <title lang="zh">香港故事</title>
  </programme>
  <programme start="20260420033500 +0800" stop="20260420040500 +0800" channel="香港卫视">
    <title lang="zh">映像</title>
  </programme>
  <programme start="20260420040500 +0800" stop="20260420043200 +0800" channel="香港卫视">
    <title lang="zh">守心人</title>
  </programme>
  <programme start="20260420043200 +0800" stop="20260420045000 +0800" channel="香港卫视">
    <title lang="zh">那点财经事</title>
  </programme>
  <programme start="20260420045000 +0800" stop="20260420052000 +0800" channel="香港卫视">
    <title lang="zh">高朋满座</title>
  </programme>
  <programme start="20260420052000 +0800" stop="20260420054400 +0800" channel="香港卫视">
    <title lang="zh">西望成都</title>
  </programme>
  <programme start="20260420054400 +0800" stop="20260420061500 +0800" channel="香港卫视">
    <title lang="zh">讲述者 第二季</title>
  </programme>
  <programme start="20260420061500 +0800" stop="20260420064500 +0800" channel="香港卫视">
    <title lang="zh">香港故事</title>
  </programme>
  <programme start="20260420064500 +0800" stop="20260420070900 +0800" channel="香港卫视">
    <title lang="zh">东边西边</title>
  </programme>
  <programme start="20260420070900 +0800" stop="20260420071500 +0800" channel="香港卫视">
    <title lang="zh">香港故事</title>
  </programme>
  <programme start="20260420071500 +0800" stop="20260420072500 +0800" channel="香港卫视">
    <title lang="zh">印象重庆</title>
  </programme>
  <programme start="20260420072500 +0800" stop="20260420073800 +0800" channel="香港卫视">
    <title lang="zh">印象重庆</title>
  </programme>
  <programme start="20260420073800 +0800" stop="20260420080500 +0800" channel="香港卫视">
    <title lang="zh">独爱东南</title>
  </programme>
  <programme start="20260420080500 +0800" stop="20260420081800 +0800" channel="香港卫视">
    <title lang="zh">印象重庆</title>
  </programme>
  <programme start="20260420081800 +0800" stop="20260420095500 +0800" channel="香港卫视">
    <title lang="zh">港视剧场</title>
  </programme>
  <programme start="20260420095500 +0800" stop="20260420102500 +0800" channel="香港卫视">
    <title lang="zh">西望成都</title>
  </programme>
  <programme start="20260420102500 +0800" stop="20260420103700 +0800" channel="香港卫视">
    <title lang="zh">非凡讲述</title>
  </programme>
  <programme start="20260420103700 +0800" stop="20260420110700 +0800" channel="香港卫视">
    <title lang="zh">文化超声</title>
  </programme>
  <programme start="20260420110700 +0800" stop="20260420112400 +0800" channel="香港卫视">
    <title lang="zh">亚洲青年说</title>
  </programme>
  <programme start="20260420112400 +0800" stop="20260420115500 +0800" channel="香港卫视">
    <title lang="zh">文化超声</title>
  </programme>
  <programme start="20260420115500 +0800" stop="20260420123000 +0800" channel="香港卫视">
    <title lang="zh">映像</title>
  </programme>
  <programme start="20260420123000 +0800" stop="20260420125000 +0800" channel="香港卫视">
    <title lang="zh">《黄山非遗•大师说》</title>
  </programme>
  <programme start="20260420125000 +0800" stop="20260420131100 +0800" channel="香港卫视">
    <title lang="zh">西望成都</title>
  </programme>
  <programme start="20260420131100 +0800" stop="20260420133200 +0800" channel="香港卫视">
    <title lang="zh">童言有艺</title>
  </programme>
  <programme start="20260420133200 +0800" stop="20260420134800 +0800" channel="香港卫视">
    <title lang="zh">品牌中国行</title>
  </programme>
  <programme start="20260420134800 +0800" stop="20260420141600 +0800" channel="香港卫视">
    <title lang="zh">独爱东南</title>
  </programme>
  <programme start="20260420141600 +0800" stop="20260420143500 +0800" channel="香港卫视">
    <title lang="zh">《黄山非遗•大师说》</title>
  </programme>
  <programme start="20260420143500 +0800" stop="20260420150400 +0800" channel="香港卫视">
    <title lang="zh">映像</title>
  </programme>
  <programme start="20260420150400 +0800" stop="20260420152000 +0800" channel="香港卫视">
    <title lang="zh">亚洲青年说</title>
  </programme>
  <programme start="20260420152000 +0800" stop="20260420152200 +0800" channel="香港卫视">
    <title lang="zh">美丽中国</title>
  </programme>
  <programme start="20260420152200 +0800" stop="20260420155400 +0800" channel="香港卫视">
    <title lang="zh">纪录东方</title>
  </programme>
  <programme start="20260420155400 +0800" stop="20260420160500 +0800" channel="香港卫视">
    <title lang="zh">印象重庆</title>
  </programme>
  <programme start="20260420160500 +0800" stop="20260420163500 +0800" channel="香港卫视">
    <title lang="zh">美丽中华行</title>
  </programme>
  <programme start="20260420163500 +0800" stop="20260420170200 +0800" channel="香港卫视">
    <title lang="zh">西望成都</title>
  </programme>
  <programme start="20260420170200 +0800" stop="20260420173000 +0800" channel="香港卫视">
    <title lang="zh">独爱东南</title>
  </programme>
  <programme start="20260420173000 +0800" stop="20260420180000 +0800" channel="香港卫视">
    <title lang="zh">守心人</title>
  </programme>
  <programme start="20260420180000 +0800" stop="20260420181000 +0800" channel="香港卫视">
    <title lang="zh">新闻纵览</title>
  </programme>
  <programme start="20260420181000 +0800" stop="20260420182100 +0800" channel="香港卫视">
    <title lang="zh">印象重庆</title>
  </programme>
  <programme start="20260420182100 +0800" stop="20260420200000 +0800" channel="香港卫视">
    <title lang="zh">港视剧场</title>
  </programme>
  <programme start="20260420200000 +0800" stop="20260420202000 +0800" channel="香港卫视">
    <title lang="zh">西望成都</title>
  </programme>
  <programme start="20260420202000 +0800" stop="20260420203000 +0800" channel="香港卫视">
    <title lang="zh">印象重庆</title>
  </programme>
  <programme start="20260420203000 +0800" stop="20260420205900 +0800" channel="香港卫视">
    <title lang="zh">东边西边</title>
  </programme>
  <programme start="20260420205900 +0800" stop="20260420213000 +0800" channel="香港卫视">
    <title lang="zh">鲁茶的足迹</title>
  </programme>
  <programme start="20260420213000 +0800" stop="20260420214500 +0800" channel="香港卫视">
    <title lang="zh">亚洲人物</title>
  </programme>
  <programme start="20260420214500 +0800" stop="20260420220000 +0800" channel="香港卫视">
    <title lang="zh">亚洲人物</title>
  </programme>
  <programme start="20260420220000 +0800" stop="20260420221700 +0800" channel="香港卫视">
    <title lang="zh">亚洲青年说</title>
  </programme>
  <programme start="20260420221700 +0800" stop="20260420224700 +0800" channel="香港卫视">
    <title lang="zh">文化超声</title>
  </programme>
  <programme start="20260420224700 +0800" stop="20260420230000 +0800" channel="香港卫视">
    <title lang="zh">寿乡密码</title>
  </programme>
  <programme start="20260420230000 +0800" stop="20260420232200 +0800" channel="香港卫视">
    <title lang="zh">香江唱皖</title>
  </programme>
  <programme start="20260420232200 +0800" stop="20260420235000 +0800" channel="香港卫视">
    <title lang="zh">东边西边</title>
  </programme>
  <programme start="20260420235000 +0800" stop="20260421001100 +0800" channel="香港卫视">
    <title lang="zh">《黄山非遗•大师说》</title>
  </programme>
  <programme start="20260421001100 +0800" stop="20260421004100 +0800" channel="香港卫视">
    <title lang="zh">映像</title>
  </programme>
  <programme start="20260421004100 +0800" stop="20260421011100 +0800" channel="香港卫视">
    <title lang="zh">独爱东南</title>
  </programme>
  <programme start="20260421011100 +0800" stop="20260421014500 +0800" channel="香港卫视">
    <title lang="zh">文化超声</title>
  </programme>
  <programme start="20260421014500 +0800" stop="20260421020500 +0800" channel="香港卫视">
    <title lang="zh">亚洲人物</title>
  </programme>
  <programme start="20260421020500 +0800" stop="20260421022500 +0800" channel="香港卫视">
    <title lang="zh">亚洲人物</title>
  </programme>
  <programme start="20260421022500 +0800" stop="20260421024500 +0800" channel="香港卫视">
    <title lang="zh">亚洲人物</title>
  </programme>
  <programme start="20260421024500 +0800" stop="20260421030400 +0800" channel="香港卫视">
    <title lang="zh">亚洲人物</title>
  </programme>
  <programme start="20260421030400 +0800" stop="20260421033500 +0800" channel="香港卫视">
    <title lang="zh">香港故事</title>
  </programme>
  <programme start="20260421033500 +0800" stop="20260421040500 +0800" channel="香港卫视">
    <title lang="zh">映像</title>
  </programme>
  <programme start="20260421040500 +0800" stop="20260421043000 +0800" channel="香港卫视">
    <title lang="zh">守心人</title>
  </programme>
  <programme start="20260421043000 +0800" stop="20260421043200 +0800" channel="香港卫视">
    <title lang="zh">高朋满座</title>
  </programme>
  <programme start="20260421043200 +0800" stop="20260421045000 +0800" channel="香港卫视">
    <title lang="zh">那点财经事</title>
  </programme>
  <programme start="20260421045000 +0800" stop="20260421052000 +0800" channel="香港卫视">
    <title lang="zh">高朋满座</title>
  </programme>
  <programme start="20260421052000 +0800" stop="20260421054500 +0800" channel="香港卫视">
    <title lang="zh">香江唱皖</title>
  </programme>
  <programme start="20260421054500 +0800" stop="20260421061500 +0800" channel="香港卫视">
    <title lang="zh">文化超声</title>
  </programme>
  <programme start="20260421061500 +0800" stop="20260421064500 +0800" channel="香港卫视">
    <title lang="zh">香港故事</title>
  </programme>
  <programme start="20260421064500 +0800" stop="20260421071500 +0800" channel="香港卫视">
    <title lang="zh">东边西边</title>
  </programme>
  <programme start="20260421071500 +0800" stop="20260421072500 +0800" channel="香港卫视">
    <title lang="zh">印象重庆</title>
  </programme>
  <programme start="20260421072500 +0800" stop="20260421073300 +0800" channel="香港卫视">
    <title lang="zh">早安中国</title>
  </programme>
  <programme start="20260421073300 +0800" stop="20260421080000 +0800" channel="香港卫视">
    <title lang="zh">独爱东南</title>
  </programme>
  <programme start="20260421080000 +0800" stop="20260421080500 +0800" channel="香港卫视">
    <title lang="zh">早安中国</title>
  </programme>
  <programme start="20260421080500 +0800" stop="20260421083000 +0800" channel="香港卫视">
    <title lang="zh">香江唱皖</title>
  </programme>
  <programme start="20260421083000 +0800" stop="20260421090000 +0800" channel="香港卫视">
    <title lang="zh">映像</title>
  </programme>
  <programme start="20260421090000 +0800" stop="20260421090500 +0800" channel="香港卫视">
    <title lang="zh">早安中国</title>
  </programme>
  <programme start="20260421090500 +0800" stop="20260421093000 +0800" channel="香港卫视">
    <title lang="zh">守心人</title>
  </programme>
  <programme start="20260421093000 +0800" stop="20260421100000 +0800" channel="香港卫视">
    <title lang="zh">东边西边</title>
  </programme>
  <programme start="20260421100000 +0800" stop="20260421100500 +0800" channel="香港卫视">
    <title lang="zh">早安中国</title>
  </programme>
  <programme start="20260421100500 +0800" stop="20260421103000 +0800" channel="香港卫视">
    <title lang="zh">独爱东南</title>
  </programme>
  <programme start="20260421103000 +0800" stop="20260421110700 +0800" channel="香港卫视">
    <title lang="zh">美丽中华行</title>
  </programme>
  <programme start="20260421110700 +0800" stop="20260421112500 +0800" channel="香港卫视">
    <title lang="zh">亚洲青年说</title>
  </programme>
  <programme start="20260421112500 +0800" stop="20260421115500 +0800" channel="香港卫视">
    <title lang="zh">文化超声</title>
  </programme>
  <programme start="20260421115500 +0800" stop="20260421123000 +0800" channel="香港卫视">
    <title lang="zh">高朋满座</title>
  </programme>
  <programme start="20260421123000 +0800" stop="20260421125000 +0800" channel="香港卫视">
    <title lang="zh">《黄山非遗•大师说》</title>
  </programme>
  <programme start="20260421125000 +0800" stop="20260421131600 +0800" channel="香港卫视">
    <title lang="zh">独爱东南</title>
  </programme>
  <programme start="20260421131600 +0800" stop="20260421134500 +0800" channel="香港卫视">
    <title lang="zh">香港精神</title>
  </programme>
  <programme start="20260421134500 +0800" stop="20260421140500 +0800" channel="香港卫视">
    <title lang="zh">西望成都</title>
  </programme>
  <programme start="20260421140500 +0800" stop="20260421142500 +0800" channel="香港卫视">
    <title lang="zh">《黄山非遗•大师说》</title>
  </programme>
  <programme start="20260421142500 +0800" stop="20260421144500 +0800" channel="香港卫视">
    <title lang="zh">亚洲人物</title>
  </programme>
  <programme start="20260421144500 +0800" stop="20260421151500 +0800" channel="香港卫视">
    <title lang="zh">东边西边</title>
  </programme>
  <programme start="20260421151500 +0800" stop="20260421153200 +0800" channel="香港卫视">
    <title lang="zh">亚洲青年说</title>
  </programme>
  <programme start="20260421153200 +0800" stop="20260421160000 +0800" channel="香港卫视">
    <title lang="zh">文化超声</title>
  </programme>
  <programme start="20260421160000 +0800" stop="20260421163500 +0800" channel="香港卫视">
    <title lang="zh">文化超声</title>
  </programme>
  <programme start="20260421163500 +0800" stop="20260421171000 +0800" channel="香港卫视">
    <title lang="zh">高朋满座</title>
  </programme>
  <programme start="20260421171000 +0800" stop="20260421172600 +0800" channel="香港卫视">
    <title lang="zh">岚山味道</title>
  </programme>
  <programme start="20260421172600 +0800" stop="20260421174700 +0800" channel="香港卫视">
    <title lang="zh">美丽中国-岚山味道</title>
  </programme>
  <programme start="20260421174700 +0800" stop="20260421180000 +0800" channel="香港卫视">
    <title lang="zh">印象重庆</title>
  </programme>
  <programme start="20260421180000 +0800" stop="20260421181500 +0800" channel="香港卫视">
    <title lang="zh">新闻纵览</title>
  </programme>
  <programme start="20260421181500 +0800" stop="20260421183100 +0800" channel="香港卫视">
    <title lang="zh">黄山非遗•大师说</title>
  </programme>
  <programme start="20260421183100 +0800" stop="20260421184400 +0800" channel="香港卫视">
    <title lang="zh">动画天地</title>
  </programme>
  <programme start="20260421184400 +0800" stop="20260421185700 +0800" channel="香港卫视">
    <title lang="zh">动画天地</title>
  </programme>
  <programme start="20260421185700 +0800" stop="20260421190000 +0800" channel="香港卫视">
    <title lang="zh">美丽中国</title>
  </programme>
  <programme start="20260421190000 +0800" stop="20260421193000 +0800" channel="香港卫视">
    <title lang="zh">美丽中华行</title>
  </programme>
  <programme start="20260421193000 +0800" stop="20260421200000 +0800" channel="香港卫视">
    <title lang="zh">东边西边</title>
  </programme>
  <programme start="20260421200000 +0800" stop="20260421203000 +0800" channel="香港卫视">
    <title lang="zh">香港精神</title>
  </programme>
  <programme start="20260421203000 +0800" stop="20260421210000 +0800" channel="香港卫视">
    <title lang="zh">东边西边</title>
  </programme>
  <programme start="20260421210000 +0800" stop="20260421212000 +0800" channel="香港卫视">
    <title lang="zh">西望成都</title>
  </programme>
  <programme start="20260421212000 +0800" stop="20260421213000 +0800" channel="香港卫视">
    <title lang="zh">印象重庆</title>
  </programme>
  <programme start="20260421213000 +0800" stop="20260421214500 +0800" channel="香港卫视">
    <title lang="zh">中国品牌行</title>
  </programme>
  <programme start="20260421214500 +0800" stop="20260421220000 +0800" channel="香港卫视">
    <title lang="zh">印象重庆</title>
  </programme>
  <programme start="20260421220000 +0800" stop="20260421223000 +0800" channel="香港卫视">
    <title lang="zh">美丽中华行</title>
  </programme>
  <programme start="20260421223000 +0800" stop="20260421230000 +0800" channel="香港卫视">
    <title lang="zh">美丽中国-岚山味道</title>
  </programme>
  <programme start="20260421230000 +0800" stop="20260421232200 +0800" channel="香港卫视">
    <title lang="zh">香江唱皖</title>
  </programme>
  <programme start="20260421232200 +0800" stop="20260421235000 +0800" channel="香港卫视">
    <title lang="zh">东边西边</title>
  </programme>
  <programme start="20260421235000 +0800" stop="20260422000000 +0800" channel="香港卫视">
    <title lang="zh">《黄山非遗•大师说》</title>
  </programme>
</tv>
